{
  "editor_signature": "l2d_config_editor/v1",
  "global_mode": "simple",
  "interaction_creation_mode": "auto",
  "editor_settings": {
    "numeric_linkage_enabled": true,
    "trash_enabled": true
  },
  "meta": {
    "version": "2099-09-09",
    "author": "123123",
    "ship_skin_id": 1231230,
    "memo": "123123",
    "react_condition": "123123",
    "tips": "123123",
    "CharName": "123123"
  },
  "nodes": [
    {
      "uuid": "ce46f7db0d5a4fbfa05aabf1c2005141",
      "type": "Initial",
      "ui_position": {
        "x": 72.0,
        "y": 72.0
      },
      "locked": false,
      "tips": "123123",
      "version": "2099-09-09",
      "CharName": "123123",
      "memo": "123123",
      "ship_skin_id": 1231230,
      "react_condition": "123123",
      "author": "123123"
    },
    {
      "uuid": "cefdf0ec9f474d3da25b6f4d53129efe",
      "type": "TouchIdle",
      "ui_position": {
        "x": 636.2,
        "y": 72.0
      },
      "type_slot": 1,
      "export_slot": 1,
      "locked": false,
      "tips": "",
      "desc": "",
      "draw_able_name": "TouchIdle1",
      "parameter": "Paramtouch_idle1",
      "range": "{0,1}",
      "control_type": "click",
      "drag_ui_direction": "",
      "transition_type": "animated",
      "action_trigger": "{type = 2 ,action = 'touch_idle1'}",
      "action_trigger_active": "{enable = {},ignore = {{'main_1','main_2','main_3','main_4','mission','mission_complete','complete','login','home','mail','touch_body','touch_head'}},idle = 1}",
      "id": 123123001,
      "mode": 1,
      "start_value": 0,
      "parts_data": "",
      "ignore_react": 1,
      "ignore_action": 1,
      "range_abs": 1,
      "drag_direct": 0,
      "react_pos_x": null,
      "react_pos_y": null,
      "offset_circle": "",
      "offset_x": 0,
      "offset_y": 0,
      "smooth": 100,
      "revert_smooth": 100,
      "revert": -1,
      "save_parameter": "",
      "gyro": 0,
      "gyro_x": 0,
      "gyro_y": 0,
      "gyro_z": 0,
      "limit_time": 1.0,
      "listener_data": "",
      "shop_action": 0,
      "relation_parameter": ""
    },
    {
      "uuid": "5bd0274d656144429952b4cbd0ade5db",
      "type": "TouchDrag",
      "ui_position": {
        "x": 1200.4,
        "y": 72.0
      },
      "type_slot": 1,
      "export_slot": 2,
      "locked": false,
      "tips": "大方向深V的鬼斧神工都是方法是大哥",
      "desc": "",
      "draw_able_name": "TouchDrag1",
      "parameter": "touch_drag1",
      "range": "{0,1}",
      "control_type": "click",
      "drag_ui_direction": "",
      "result_type": "action",
      "action_trigger": "{type = 2 ,action = 'touch_idle1'}",
      "target_value": 1.0,
      "revert_enabled": 0,
      "parts_data": "",
      "id": 123123002,
      "mode": 1,
      "start_value": 0,
      "ignore_react": 1,
      "ignore_action": 1,
      "range_abs": 1,
      "drag_direct": 0,
      "react_pos_x": null,
      "react_pos_y": null,
      "offset_circle": "",
      "offset_x": 0,
      "offset_y": 0,
      "smooth": 100,
      "revert_smooth": 100,
      "revert": -1,
      "revert_action_index": "",
      "revert_idle_index": "",
      "save_parameter": "",
      "gyro": 0,
      "gyro_x": 0,
      "gyro_y": 0,
      "gyro_z": 0,
      "limit_time": 1.0,
      "listener_data": "",
      "shop_action": 0,
      "relation_parameter": ""
    },
    {
      "uuid": "f3c4ea15f5a14c8e8e6a6b27acf06784",
      "type": "Comment",
      "ui_position": {
        "x": 1735.5859311359677,
        "y": 0.7549222112602365
      },
      "locked": false,
      "ui_size": {
        "width": 364.0,
        "height": 742.1336649407342
      },
      "note_box_color": "#8d041d",
      "note_box_alpha": 62,
      "note_text_color": "#32f842",
      "note_text_alpha": 96,
      "note_font_size": 15,
      "content": "",
      "drag_direct": 0
    },
    {
      "uuid": "0a1fc9d55b954638975c128813b02e4a",
      "type": "TouchDrag",
      "ui_position": {
        "x": 636.2,
        "y": 636.0
      },
      "type_slot": 2,
      "export_slot": 3,
      "locked": false,
      "tips": "",
      "desc": "",
      "draw_able_name": "TouchDrag2",
      "parameter": "touch_drag2",
      "range": "{0,1}",
      "control_type": "click",
      "drag_ui_direction": "",
      "result_type": "action",
      "action_trigger": "{type = 2 ,action = 'touch_idle2'}",
      "target_value": 1.0,
      "revert_enabled": 0,
      "parts_data": "",
      "id": 123123003,
      "mode": 1,
      "start_value": 0,
      "ignore_react": 1,
      "ignore_action": 1,
      "range_abs": 1,
      "drag_direct": 0,
      "react_pos_x": null,
      "react_pos_y": null,
      "offset_circle": "",
      "offset_x": 0,
      "offset_y": 0,
      "smooth": 100,
      "revert_smooth": 100,
      "revert": -1,
      "revert_action_index": "",
      "revert_idle_index": "",
      "save_parameter": "",
      "gyro": 0,
      "gyro_x": 0,
      "gyro_y": 0,
      "gyro_z": 0,
      "limit_time": 1.0,
      "listener_data": "",
      "shop_action": 0,
      "relation_parameter": ""
    },
    {
      "uuid": "4f070b2d75e748a89b41a31cd1cbeb42",
      "type": "TouchDrag",
      "ui_position": {
        "x": 636.2,
        "y": 1200.0
      },
      "type_slot": 3,
      "export_slot": 4,
      "locked": false,
      "tips": "",
      "desc": "",
      "draw_able_name": "TouchDrag3",
      "parameter": "touch_drag3",
      "range": "{0,1}",
      "control_type": "click",
      "drag_ui_direction": "",
      "result_type": "action",
      "action_trigger": "{type = 2 ,action = 'touch_idle3'}",
      "target_value": 1.0,
      "revert_enabled": 0,
      "parts_data": "",
      "id": 123123004,
      "mode": 1,
      "start_value": 0,
      "ignore_react": 1,
      "ignore_action": 1,
      "range_abs": 1,
      "drag_direct": 0,
      "react_pos_x": null,
      "react_pos_y": null,
      "offset_circle": "",
      "offset_x": 0,
      "offset_y": 0,
      "smooth": 100,
      "revert_smooth": 100,
      "revert": -1,
      "revert_action_index": "",
      "revert_idle_index": "",
      "save_parameter": "",
      "gyro": 0,
      "gyro_x": 0,
      "gyro_y": 0,
      "gyro_z": 0,
      "limit_time": 1.0,
      "listener_data": "",
      "shop_action": 0,
      "relation_parameter": ""
    },
    {
      "uuid": "f80b1f1a1d8340b4ae98bd4c86779d3d",
      "type": "TouchDrag",
      "ui_position": {
        "x": 1200.4,
        "y": 816.0
      },
      "type_slot": 4,
      "export_slot": 5,
      "locked": false,
      "tips": "",
      "desc": "",
      "draw_able_name": "TouchDrag4",
      "parameter": "touch_drag4",
      "range": "{0,1}",
      "control_type": "click",
      "drag_ui_direction": "",
      "result_type": "action",
      "action_trigger": "{type = 2 ,action = 'touch_idle4'}",
      "target_value": 1.0,
      "revert_enabled": 0,
      "parts_data": "",
      "id": 123123005,
      "mode": 1,
      "start_value": 0,
      "ignore_react": 1,
      "ignore_action": 1,
      "range_abs": 1,
      "drag_direct": 0,
      "react_pos_x": null,
      "react_pos_y": null,
      "offset_circle": "",
      "offset_x": 0,
      "offset_y": 0,
      "smooth": 100,
      "revert_smooth": 100,
      "revert": -1,
      "revert_action_index": "",
      "revert_idle_index": "",
      "save_parameter": "",
      "gyro": 0,
      "gyro_x": 0,
      "gyro_y": 0,
      "gyro_z": 0,
      "limit_time": 1.0,
      "listener_data": "",
      "shop_action": 0,
      "relation_parameter": ""
    },
    {
      "uuid": "cbeb4d3f662749b0b6047bfa919c94f4",
      "type": "TouchIdle",
      "ui_position": {
        "x": 1152.5739130434786,
        "y": 1368.4485052745129
      },
      "type_slot": 2,
      "export_slot": 6,
      "locked": false,
      "tips": "",
      "desc": "",
      "draw_able_name": "TouchIdle2",
      "parameter": "Paramtouch_idle2",
      "range": "{0,1}",
      "control_type": "click",
      "drag_ui_direction": "",
      "transition_type": "animated",
      "action_trigger": "{type = 2 ,action = 'touch_idle2'}",
      "action_trigger_active": "{enable = {},ignore = {{'main_1','main_2','main_3','main_4','mission','mission_complete','complete','login','home','mail','touch_body','touch_head'}},idle = 2}",
      "id": 123123006,
      "mode": 1,
      "start_value": 0,
      "parts_data": "",
      "ignore_react": 1,
      "ignore_action": 1,
      "range_abs": 1,
      "drag_direct": 0,
      "react_pos_x": null,
      "react_pos_y": null,
      "offset_circle": "",
      "offset_x": 0,
      "offset_y": 0,
      "smooth": 100,
      "revert_smooth": 100,
      "revert": -1,
      "save_parameter": "",
      "gyro": 0,
      "gyro_x": 0,
      "gyro_y": 0,
      "gyro_z": 0,
      "limit_time": 1.0,
      "listener_data": "",
      "shop_action": 0,
      "relation_parameter": ""
    },
    {
      "uuid": "19584160347b4315a1d2c32306ddd5ff",
      "type": "ParameterTrigger",
      "ui_position": {
        "x": 1704.4406498816707,
        "y": 821.0666451484699
      },
      "type_slot": 1,
      "export_slot": 7,
      "locked": false,
      "tips": "",
      "desc": "",
      "draw_able_name": "ParameterTrigger1",
      "parameter": "touch_drag1",
      "range": "{0,1}",
      "control_type": "click",
      "drag_ui_direction": "",
      "target_value": 1.0,
      "revert_enabled": 0,
      "parts_data": "",
      "id": 123123007,
      "mode": 1,
      "start_value": 0,
      "ignore_react": 1,
      "ignore_action": 1,
      "range_abs": 1,
      "drag_direct": 0,
      "react_pos_x": null,
      "react_pos_y": null,
      "offset_circle": "",
      "offset_x": 0,
      "offset_y": 0,
      "smooth": 100,
      "revert_smooth": 100,
      "revert": -1,
      "revert_action_index": "",
      "revert_idle_index": "",
      "save_parameter": "",
      "gyro": 0,
      "gyro_x": 0,
      "gyro_y": 0,
      "gyro_z": 0,
      "limit_time": 1.0,
      "listener_data": "",
      "shop_action": 0,
      "relation_parameter": "",
      "action_trigger": "",
      "result_type": "value"
    },
    {
      "uuid": "4c00bd0604ad4ee792f2fcd95adb8b16",
      "type": "ParameterTrigger",
      "ui_position": {
        "x": 1616.521739130435,
        "y": 1486.0869565217392
      },
      "type_slot": 2,
      "export_slot": 8,
      "locked": false,
      "tips": "",
      "desc": "",
      "draw_able_name": "ParameterTrigger2",
      "parameter": "touch_drag2",
      "range": "{0,1}",
      "control_type": "click",
      "drag_ui_direction": "",
      "target_value": 1.0,
      "revert_enabled": 0,
      "parts_data": "",
      "id": 123123008,
      "mode": 1,
      "start_value": 0,
      "ignore_react": 1,
      "ignore_action": 1,
      "range_abs": 1,
      "drag_direct": 0,
      "react_pos_x": null,
      "react_pos_y": null,
      "offset_circle": "",
      "offset_x": 0,
      "offset_y": 0,
      "smooth": 100,
      "revert_smooth": 100,
      "revert": -1,
      "revert_action_index": "",
      "revert_idle_index": "",
      "save_parameter": "",
      "gyro": 0,
      "gyro_x": 0,
      "gyro_y": 0,
      "gyro_z": 0,
      "limit_time": 1.0,
      "listener_data": "",
      "shop_action": 0,
      "relation_parameter": "",
      "action_trigger": "",
      "result_type": "value"
    }
  ],
  "connections": [
    {
      "from_uuid": "ce46f7db0d5a4fbfa05aabf1c2005141",
      "to_uuid": "cefdf0ec9f474d3da25b6f4d53129efe"
    },
    {
      "from_uuid": "cefdf0ec9f474d3da25b6f4d53129efe",
      "to_uuid": "5bd0274d656144429952b4cbd0ade5db"
    },
    {
      "from_uuid": "5bd0274d656144429952b4cbd0ade5db",
      "to_uuid": "f3c4ea15f5a14c8e8e6a6b27acf06784"
    },
    {
      "from_uuid": "ce46f7db0d5a4fbfa05aabf1c2005141",
      "to_uuid": "0a1fc9d55b954638975c128813b02e4a"
    },
    {
      "from_uuid": "ce46f7db0d5a4fbfa05aabf1c2005141",
      "to_uuid": "4f070b2d75e748a89b41a31cd1cbeb42"
    },
    {
      "from_uuid": "0a1fc9d55b954638975c128813b02e4a",
      "to_uuid": "f80b1f1a1d8340b4ae98bd4c86779d3d"
    },
    {
      "from_uuid": "4f070b2d75e748a89b41a31cd1cbeb42",
      "to_uuid": "cbeb4d3f662749b0b6047bfa919c94f4"
    },
    {
      "from_uuid": "f80b1f1a1d8340b4ae98bd4c86779d3d",
      "to_uuid": "19584160347b4315a1d2c32306ddd5ff"
    },
    {
      "from_uuid": "cbeb4d3f662749b0b6047bfa919c94f4",
      "to_uuid": "4c00bd0604ad4ee792f2fcd95adb8b16"
    }
  ],
  "trash_bin": [],
  "canvas_view": {
    "scale": 1.15,
    "offset_x": 1800.0000000000002,
    "offset_y": 1578.2608695652175
  }
}